eulumdat-0.4.0.dist-info/METADATA
eulumdat-0.4.0.dist-info/WHEEL
eulumdat/__init__.py
eulumdat/eulumdat.cpython-314-darwin.so
eulumdat-0.4.0.dist-info/RECORD
